{
  "_format": "hh-sol-cache-2",
  "files": {
    "/Users/ayushanand/Downloads/Projects practice/Dapp University/blockchain-developer-bootcamp/contracts/Token.sol": {
      "lastModificationDate": 1674425519716,
      "contentHash": "1f268c0d4789e2124b9e798e5f7313cd",
      "sourceName": "contracts/Token.sol",
      "solcConfig": {
        "version": "0.8.9",
        "settings": {
          "optimizer": {
            "enabled": false,
            "runs": 200
          },
          "outputSelection": {
            "*": {
              "*": [
                "abi",
                "evm.bytecode",
                "evm.deployedBytecode",
                "evm.methodIdentifiers",
                "metadata"
              ],
              "": [
                "ast"
              ]
            }
          }
        }
      },
      "imports": [
        "hardhat/console.sol"
      ],
      "versionPragmas": [
        "^0.8.0"
      ],
      "artifacts": [
        "Token"
      ]
    },
    "/Users/ayushanand/Downloads/Projects practice/Dapp University/blockchain-developer-bootcamp/node_modules/hardhat/console.sol": {
      "lastModificationDate": 1674336337065,
      "contentHash": "4ff3cd2f6272c9a6516e9ee4f2b967d3",
      "sourceName": "hardhat/console.sol",
      "solcConfig": {
        "version": "0.8.9",
        "settings": {
          "optimizer": {
            "enabled": false,
            "runs": 200
          },
          "outputSelection": {
            "*": {
              "*": [
                "abi",
                "evm.bytecode",
                "evm.deployedBytecode",
                "evm.methodIdentifiers",
                "metadata"
              ],
              "": [
                "ast"
              ]
            }
          }
        }
      },
      "imports": [],
      "versionPragmas": [
        ">= 0.4.22 <0.9.0"
      ],
      "artifacts": [
        "console"
      ]
    },
    "/Users/ayushanand/Downloads/Projects practice/Dapp University/blockchain-developer-bootcamp/contracts/Exchange.sol": {
      "lastModificationDate": 1674425516294,
      "contentHash": "bbcb27a3854a0136df60d52a6c606e69",
      "sourceName": "contracts/Exchange.sol",
      "solcConfig": {
        "version": "0.8.9",
        "settings": {
          "optimizer": {
            "enabled": false,
            "runs": 200
          },
          "outputSelection": {
            "*": {
              "*": [
                "abi",
                "evm.bytecode",
                "evm.deployedBytecode",
                "evm.methodIdentifiers",
                "metadata"
              ],
              "": [
                "ast"
              ]
            }
          }
        }
      },
      "imports": [
        "./Token.sol"
      ],
      "versionPragmas": [
        "^0.8.0"
      ],
      "artifacts": [
        "Exchange"
      ]
    }
  }
}
